{
	"backtraceGraph" : 
	{
		"commands" : 
		[
			"INSTALL",
			"SC_ADD_EXECUTABLE"
		],
		"files" : 
		[
			"cmake/SeisComP.cmake",
			"src/base/main/apps/tools/scardac/CMakeLists.txt"
		],
		"nodes" : 
		[
			{
				"file" : 1
			},
			{
				"command" : 1,
				"file" : 1,
				"line" : 11,
				"parent" : 0
			},
			{
				"command" : 0,
				"file" : 0,
				"line" : 521,
				"parent" : 1
			},
			{
				"command" : 0,
				"file" : 0,
				"line" : 528,
				"parent" : 1
			},
			{
				"command" : 0,
				"file" : 1,
				"line" : 17,
				"parent" : 0
			}
		]
	},
	"installers" : 
	[
		{
			"backtrace" : 2,
			"component" : "Unspecified",
			"destination" : "bin",
			"paths" : 
			[
				"bin/scardac"
			],
			"targetId" : "scardac::@65364a1a615b06bac22d",
			"targetIndex" : 93,
			"type" : "target"
		},
		{
			"backtrace" : 3,
			"component" : "Unspecified",
			"destination" : "etc/defaults",
			"paths" : 
			[
				"src/base/main/apps/tools/scardac/config/scardac.cfg"
			],
			"type" : "file"
		},
		{
			"backtrace" : 4,
			"component" : "Unspecified",
			"destination" : "etc/descriptions",
			"paths" : 
			[
				"src/base/main/apps/tools/scardac/descriptions/scardac.xml"
			],
			"type" : "file"
		}
	],
	"paths" : 
	{
		"build" : "src/base/main/apps/tools/scardac",
		"source" : "src/base/main/apps/tools/scardac"
	}
}
