{
	"backtraceGraph" : 
	{
		"commands" : 
		[
			"INSTALL",
			"SC_ADD_EXECUTABLE"
		],
		"files" : 
		[
			"cmake/SeisComP.cmake",
			"src/base/main/apps/tools/scxmlmerge/CMakeLists.txt"
		],
		"nodes" : 
		[
			{
				"file" : 1
			},
			{
				"command" : 1,
				"file" : 1,
				"line" : 6,
				"parent" : 0
			},
			{
				"command" : 0,
				"file" : 0,
				"line" : 521,
				"parent" : 1
			}
		]
	},
	"installers" : 
	[
		{
			"backtrace" : 2,
			"component" : "Unspecified",
			"destination" : "bin",
			"paths" : 
			[
				"bin/scxmlmerge"
			],
			"targetId" : "scxmlmerge::@73af6fa0cb5fe99e7ff1",
			"targetIndex" : 129,
			"type" : "target"
		}
	],
	"paths" : 
	{
		"build" : "src/base/main/apps/tools/scxmlmerge",
		"source" : "src/base/main/apps/tools/scxmlmerge"
	}
}
