{
	"backtraceGraph" : 
	{
		"commands" : 
		[
			"INSTALL"
		],
		"files" : 
		[
			"src/system/libs/3rd-party/libmseed/CMakeLists.txt"
		],
		"nodes" : 
		[
			{
				"file" : 0
			},
			{
				"command" : 0,
				"file" : 0,
				"line" : 28,
				"parent" : 0
			},
			{
				"command" : 0,
				"file" : 0,
				"line" : 33,
				"parent" : 0
			}
		]
	},
	"installers" : 
	[
		{
			"backtrace" : 1,
			"component" : "Unspecified",
			"destination" : "lib",
			"paths" : 
			[
				"lib/libmseed.so.2.19"
			],
			"targetId" : "mseed::@76aad10bdc85cbe44829",
			"targetIndex" : 72,
			"targetInstallNamelink" : "skip",
			"type" : "target"
		},
		{
			"backtrace" : 1,
			"component" : "Unspecified",
			"destination" : "lib",
			"paths" : 
			[
				"lib/libmseed.so"
			],
			"targetId" : "mseed::@76aad10bdc85cbe44829",
			"targetIndex" : 72,
			"targetInstallNamelink" : "only",
			"type" : "target"
		},
		{
			"backtrace" : 2,
			"component" : "Unspecified",
			"destination" : "include",
			"paths" : 
			[
				"src/system/libs/3rd-party/libmseed/lmplatform.h",
				"src/system/libs/3rd-party/libmseed/libmseed.h"
			],
			"type" : "file"
		}
	],
	"paths" : 
	{
		"build" : "src/system/libs/3rd-party/libmseed",
		"source" : "src/system/libs/3rd-party/libmseed"
	}
}
